{
  "name": "א",
  "gridCount": 3,
  "data": [
    {
      "index": 0,
      "gridIndex": 0,
      "rel": 3
    },
    {
      "index": 1,
      "gridIndex": 2,
      "rel": 2
    },
    {
      "index": 2,
      "gridIndex": 3,
      "rel": 5
    },
    {
      "index": 3,
      "gridIndex": 5,
      "rel": 4
    },
    {
      "index": 4,
      "gridIndex": 9,
      "rel": 6
    },
    {
      "index": 5,
      "gridIndex": 11,
      "rel": 7
    },
    {
      "index": 6,
      "gridIndex": 12,
      "rel": 8
    },
    {
      "index": 7,
      "gridIndex": 14,
      "rel": 4
    },
    {
      "index": 8,
      "gridIndex": 16,
      "rel": 9
    },
    {
      "index": 9,
      "gridIndex": 17,
      "rel": ""
    },
    {
      "index": 10,
      "gridIndex": 19,
      "rel": 7
    }
  ]
}